bel/Config.py
bel/__init__.py
bel/__version__.py
bel/scripts.py
bel/setup_logging.py
bel/utils.py
bel/db/__init__.py
bel/db/arangodb.py
bel/db/elasticsearch.py
bel/db/es_mapping_terms.yml
bel/db/es_mappings_terms.yml
bel/edge/__init__.py
bel/edge/computed.py
bel/edge/edges.py
bel/edge/pipeline.py
bel/lang/__init__.py
bel/lang/ast.py
bel/lang/bel_specification.py
bel/lang/bel_utils.py
bel/lang/belobj.py
bel/lang/completion.py
bel/lang/computed_edges.py
bel/lang/exceptions.py
bel/lang/migrate_1_2.py
bel/lang/migrate_bel.py
bel/lang/partialparse.py
bel/lang/semantics.py
bel/lang/tools.py
bel/lang/versions/__init__.py
bel/lang/versions/bel.ebnf.j2
bel/lang/versions/bel_v2_0_0.ebnf
bel/lang/versions/bel_v2_0_0.json
bel/lang/versions/bel_v2_0_0.yaml
bel/lang/versions/bel_versions.json
bel/lang/versions/parser_v2_0_0.py
bel/lang/versions/test.bel
bel/nanopub/__init__.py
bel/nanopub/belscripts.py
bel/nanopub/files.py
bel/nanopub/nanopubs.py
bel/nanopub/nanopubstore.py
bel/nanopub/pubmed.py
bel/nanopub/validate.py
bel/resources/__init__.py
bel/resources/namespace.py
bel/resources/ortholog.py
bel/resources/resource.py
bel/terms/__init__.py
bel/terms/orthologs.py
bel/terms/terms.py
bel-0.13.1.dist-info/LICENSE
bel-0.13.1.dist-info/METADATA
bel-0.13.1.dist-info/WHEEL
bel-0.13.1.dist-info/entry_points.txt
bel-0.13.1.dist-info/top_level.txt
bel-0.13.1.dist-info/RECORD
