Metadata-Version: 2.1
Name: bel
Version: 0.13.1
Summary: BEL related functionality
Home-page: https://github.com/belbio/bel
Author: William Hayes
Author-email: whayes@biodati.com
License: Apache2
Platform: UNKNOWN
Classifier: License :: OSI Approved :: Apache Software License
Classifier: Programming Language :: Python
Classifier: Programming Language :: Python :: 3.6
Classifier: Programming Language :: Python :: 3.7
Classifier: Programming Language :: Python :: Implementation :: CPython
Classifier: Intended Audience :: Science/Research
Classifier: Development Status :: 4 - Beta
Requires-Python: ~=3.6
Requires-Dist: cityhash
Requires-Dist: click
Requires-Dist: elasticsearch (<7,>=6)
Requires-Dist: fastcache
Requires-Dist: Jinja2
Requires-Dist: jsonschema
Requires-Dist: lxml
Requires-Dist: python-arango (>=5.1)
Requires-Dist: python-dateutil
Requires-Dist: python-json-logger
Requires-Dist: pyyaml (>5)
Requires-Dist: requests
Requires-Dist: requests-cache
Requires-Dist: structlog
Requires-Dist: timy
Requires-Dist: TatSu
Requires-Dist: ulid-py
